{
  "submission_id": "virtualhome_417_1_1764118641147",
  "status": "success",
  "timestamp": "2025-11-26T08:57:21.149641",
  "goal": {
    "natural_language": "I will load the dirty clothes into the washing machine.",
    "interpreted": "i_will"
  },
  "subgoals": {
    "count": 1,
    "list": [
      {
        "id": "atomic_1",
        "description": "Execute atomic action: i_will",
        "ltl_formula": "i_will",
        "subgoal_type": "ATOMIC",
        "dependencies": [],
        "priority": 0,
        "estimated_cost": 0.92,
        "preconditions": [
          "agent_available"
        ],
        "effects": [
          "i_will"
        ],
        "metadata": {
          "depth": 0,
          "type": "atomic",
          "original_formula": "i_will",
          "feasibility_score": 0.6,
          "action_type": "general"
        }
      }
    ]
  },
  "execution_time": 0.0017113685607910156,
  "execution_times": {
    "goal_interpretation": 0.0001709461212158203,
    "subgoal_decomposition": 0.0005242824554443359,
    "transition_modeling": 0.00021076202392578125,
    "action_sequencing": 0.0002446174621582031
  },
  "debug_info": {
    "submission_id": "virtualhome_417_1_1764118641147",
    "task_id": "417_1",
    "dataset": "virtualhome",
    "natural_goal": "I will load the dirty clothes into the washing machine.",
    "start_time": "2025-11-26T08:57:21.147937",
    "modules": {
      "goal_interpretation": {
        "status": "success",
        "formula": "i_will",
        "type": "LTLFormula"
      },
      "subgoal_decomposition": {
        "status": "success",
        "subgoal_count": 1,
        "subgoals": [
          {
            "id": "atomic_1",
            "description": "Execute atomic action: i_will",
            "ltl_formula": "i_will",
            "subgoal_type": "ATOMIC",
            "dependencies": [],
            "priority": 0,
            "estimated_cost": 0.92,
            "preconditions": [
              "agent_available"
            ],
            "effects": [
              "i_will"
            ],
            "metadata": {
              "depth": 0,
              "type": "atomic",
              "original_formula": "i_will",
              "feasibility_score": 0.6,
              "action_type": "general"
            }
          }
        ],
        "type": "IntegrationResult"
      },
      "transition_modeling": {
        "status": "success",
        "type": "ModelingResponse"
      },
      "action_sequencing": {
        "status": "failed",
        "type": "SequencingResponse"
      }
    },
    "execution_times": {
      "goal_interpretation": 0.0001709461212158203,
      "subgoal_decomposition": 0.0005242824554443359,
      "transition_modeling": 0.00021076202392578125,
      "action_sequencing": 0.0002446174621582031
    }
  }
}