{
  "submission_id": "virtualhome_954_2_1764123310079",
  "status": "failed",
  "error": "Action sequencing failed: name 'Action' is not defined",
  "debug_info": {
    "submission_id": "virtualhome_954_2_1764123310079",
    "task_id": "954_2",
    "dataset": "virtualhome",
    "natural_goal": "I need to get the dirty clothes basket.  Walk to bathroom.  Put all the clothes in washing machine.  Add soap.  Turn on machine.",
    "start_time": "2025-11-26T10:15:10.079597",
    "modules": {
      "goal_interpretation": {
        "status": "success",
        "type": "LTLFormula",
        "ltl_formula": "i_need",
        "is_valid": true
      },
      "subgoal_decomposition": {
        "status": "success",
        "subgoal_count": 1,
        "subgoals": [
          {
            "id": "subgoal_0",
            "description": "完成主要任务: I need to get the dirty clothes basket.  Walk to bathroom.  Put all the clothes in washing machine.  Add soap.  Turn on machine.",
            "ltl_formula": "i_need",
            "subgoal_type": "atomic",
            "preconditions": [
              "agent_available"
            ],
            "effects": [
              "task_completed"
            ]
          }
        ],
        "type": "IntegratedDecompositionResult",
        "ltl_formula_used": ""
      },
      "transition_modeling": {
        "status": "success",
        "type": "IntegratedModelingResult"
      },
      "action_sequencing": {
        "status": "failed",
        "error": "name 'Action' is not defined"
      }
    },
    "execution_times": {
      "goal_interpretation": 0.0002491474151611328,
      "subgoal_decomposition": 0.00013875961303710938,
      "transition_modeling": 0.00015854835510253906,
      "action_sequencing": 7.033348083496094e-05
    }
  }
}